arxsite/__init__.py
arxsite/arxiv_parser.py
arxsite/cli.py
arxsite/icon.png
arxsite/index.md
arxsite/jekyll_generator.py
arxsite/teaser.png
arxsite/version.py
arxsite/templates/default/_config.yml.j2
arxsite/templates/default/default.html
arxsite/templates/default/dics.css
arxsite/templates/default/dics.js
arxsite/templates/default/style.css
arxsite-0.2.4.dist-info/licenses/LICENSE
arxsite-0.2.4.dist-info/METADATA
arxsite-0.2.4.dist-info/WHEEL
arxsite-0.2.4.dist-info/entry_points.txt
arxsite-0.2.4.dist-info/top_level.txt
arxsite-0.2.4.dist-info/RECORD
